mashumaro/__init__.py
mashumaro/config.py
mashumaro/dialect.py
mashumaro/exceptions.py
mashumaro/helper.py
mashumaro/py.typed
mashumaro/types.py
mashumaro/codecs/__init__.py
mashumaro/codecs/_builder.py
mashumaro/codecs/basic.py
mashumaro/codecs/json.py
mashumaro/codecs/msgpack.py
mashumaro/codecs/orjson.py
mashumaro/codecs/toml.py
mashumaro/codecs/yaml.py
mashumaro/core/__init__.py
mashumaro/core/const.py
mashumaro/core/helpers.py
mashumaro/core/meta/__init__.py
mashumaro/core/meta/helpers.py
mashumaro/core/meta/mixin.py
mashumaro/core/meta/code/__init__.py
mashumaro/core/meta/code/builder.py
mashumaro/core/meta/code/lines.py
mashumaro/core/meta/types/__init__.py
mashumaro/core/meta/types/common.py
mashumaro/core/meta/types/pack.py
mashumaro/core/meta/types/unpack.py
mashumaro/jsonschema/__init__.py
mashumaro/jsonschema/annotations.py
mashumaro/jsonschema/builder.py
mashumaro/jsonschema/dialects.py
mashumaro/jsonschema/models.py
mashumaro/jsonschema/plugins.py
mashumaro/jsonschema/schema.py
mashumaro/mixins/__init__.py
mashumaro/mixins/dict.py
mashumaro/mixins/json.py
mashumaro/mixins/msgpack.py
mashumaro/mixins/orjson.py
mashumaro/mixins/orjson.pyi
mashumaro/mixins/toml.py
mashumaro/mixins/yaml.py
mashumaro-3.18.dist-info/licenses/LICENSE
mashumaro-3.18.dist-info/METADATA
mashumaro-3.18.dist-info/WHEEL
mashumaro-3.18.dist-info/top_level.txt
mashumaro-3.18.dist-info/RECORD
